clicknick/__init__.py
clicknick/__main__.py
clicknick/app.py
clicknick/config.py
clicknick/py.typed
clicknick/data/__init__.py
clicknick/data/address_store.py
clicknick/data/data_source.py
clicknick/data/edit_session_new.py
clicknick/data/file_monitor.py
clicknick/data/nickname_manager.py
clicknick/data/shared_dataview.py
clicknick/data/undo_frame.py
clicknick/detection/__init__.py
clicknick/detection/window_detector.py
clicknick/detection/window_mapping.py
clicknick/models/__init__.py
clicknick/models/address_row.py
clicknick/models/blocktag.py
clicknick/models/constants.py
clicknick/models/dataview_row.py
clicknick/models/mutable_row_builder.py
clicknick/models/nickname.py
clicknick/models/validation.py
clicknick/resources/__init__.py
clicknick/resources/icon_data.py
clicknick/services/__init__.py
clicknick/services/block_service.py
clicknick/services/import_service.py
clicknick/services/nickname_index_service.py
clicknick/services/row_service.py
clicknick/utils/__init__.py
clicknick/utils/debug_trace.py
clicknick/utils/filters.py
clicknick/utils/mdb_operations.py
clicknick/utils/mdb_shared.py
clicknick/utils/rename_helpers.py
clicknick/utils/verification.py
clicknick/utils/win32_utils.py
clicknick/views/__init__.py
clicknick/views/dialogs.py
clicknick/views/overlay.py
clicknick/views/address_editor/__init__.py
clicknick/views/address_editor/cell_note.py
clicknick/views/address_editor/jump_sidebar.py
clicknick/views/address_editor/panel.py
clicknick/views/address_editor/panel_constants.py
clicknick/views/address_editor/row_styler.py
clicknick/views/address_editor/sheet.py
clicknick/views/address_editor/tab_state.py
clicknick/views/address_editor/view_builder.py
clicknick/views/address_editor/window.py
clicknick/views/dataview_editor/__init__.py
clicknick/views/dataview_editor/cdv_file.py
clicknick/views/dataview_editor/panel.py
clicknick/views/dataview_editor/window.py
clicknick/views/nav_window/__init__.py
clicknick/views/nav_window/block_panel.py
clicknick-0.17.2.dist-info/METADATA
clicknick-0.17.2.dist-info/WHEEL
clicknick-0.17.2.dist-info/entry_points.txt
clicknick-0.17.2.dist-info/licenses/LICENSE
clicknick-0.17.2.dist-info/RECORD
