Metadata-Version: 2.4
Name: clicknick
Version: 0.17.2
Summary: Tag-Based Programming for Automation Direct CLICK PLCs.
Project-URL: Repository, https://github.com/ssweber/clicknick
Author-email: ssweber <57631333+ssweber@users.noreply.github.com>
License-Expression: AGPL-3.0
License-File: LICENSE
Classifier: Development Status :: 4 - Beta
Classifier: Intended Audience :: End Users/Desktop
Classifier: Operating System :: Microsoft :: Windows
Classifier: Programming Language :: Python
Classifier: Programming Language :: Python :: 3
Classifier: Programming Language :: Python :: 3.11
Classifier: Programming Language :: Python :: 3.12
Classifier: Programming Language :: Python :: 3.13
Classifier: Typing :: Typed
Requires-Python: <4.0,>=3.11
Requires-Dist: pyodbc>=5.3.0
Requires-Dist: pywin32>=311
Requires-Dist: tksheet==7.5.19
